unit_tokenizer/__init__.py
unit_tokenizer/base_tokenizer.py
unit_tokenizer/bpe_tokenizer.py
unit_tokenizer/fast_bpe_tokenizer.py
unit_tokenizer/naive_packbits_tokenizer.py
unit_tokenizer/packbits_tokenizer.py
unit_tokenizer/rle_tokenizer.py
unit_tokenizer-0.1.7.dist-info/LICENSE
unit_tokenizer-0.1.7.dist-info/METADATA
unit_tokenizer-0.1.7.dist-info/WHEEL
unit_tokenizer-0.1.7.dist-info/top_level.txt
unit_tokenizer-0.1.7.dist-info/RECORD
