Metadata-Version: 2.2
Name: unit-tokenizer
Version: 0.1.7
Summary: Tokenizers that operate on integer sequences.
Home-page: https://github.com/cromz22/unit-tokenizer
Author: Shuichiro Shimizu
Author-email: sshimizu@nlp.ist.i.kyoto-u.ac.jp
Classifier: Programming Language :: Python :: 3.9
Classifier: License :: OSI Approved :: MIT License
Classifier: Operating System :: OS Independent
Requires-Python: >=3.9
License-File: LICENSE
Provides-Extra: dev
Requires-Dist: pytest==8.2.1; extra == "dev"
Requires-Dist: black==24.4.2; extra == "dev"
Requires-Dist: isort==5.13.2; extra == "dev"
Dynamic: author
Dynamic: author-email
Dynamic: classifier
Dynamic: description
Dynamic: description-content-type
Dynamic: home-page
Dynamic: provides-extra
Dynamic: requires-python
Dynamic: summary
